lottery_ticket_pruner/__init__.py
lottery_ticket_pruner/keras_pruner_callback.py
lottery_ticket_pruner/lottery_ticket_pruner.py
lottery_ticket_pruner-0.8.1.dist-info/LICENSE
lottery_ticket_pruner-0.8.1.dist-info/METADATA
lottery_ticket_pruner-0.8.1.dist-info/WHEEL
lottery_ticket_pruner-0.8.1.dist-info/top_level.txt
lottery_ticket_pruner-0.8.1.dist-info/RECORD
