Metadata-Version: 2.1
Name: lottery-ticket-pruner
Version: 0.8.1
Summary: Enables pruning of Keras DNNs using "lottery ticket" pruning
Home-page: https://github.com/jim-meyer/lottery_ticket_pruner
Author: Jim Meyer
Author-email: jimm@racemed.com
License: UNKNOWN
Platform: UNKNOWN
Classifier: Programming Language :: Python :: 3
Classifier: Development Status :: 4 - Beta
Classifier: License :: OSI Approved :: MIT License
Classifier: Operating System :: OS Independent
Classifier: Intended Audience :: Developers
Classifier: Intended Audience :: Education
Classifier: Intended Audience :: Science/Research
Classifier: Topic :: Scientific/Engineering :: Artificial Intelligence
Classifier: Topic :: Scientific/Engineering :: Image Recognition
Classifier: Topic :: Software Development :: Libraries :: Python Modules
Classifier: Topic :: Software Development :: Libraries
Requires-Python: >=3.6
Requires-Dist: keras (>=2.1.0)
Requires-Dist: numpy (>=1.18.3)
